{
  "featured": {
    "latest_date": "2026-03-11",
    "yesterday": "HIT",
    "last_7_days": {
      "wins": 4,
      "losses": 4,
      "hit_rate": 0.5
    },
    "season_to_date": {
      "wins": 18,
      "losses": 25,
      "hit_rate": 0.419
    }
  },
  "top_model": {
    "latest_date": "2026-03-11",
    "yesterday": "HIT",
    "last_7_days": {
      "wins": 4,
      "losses": 4,
      "hit_rate": 0.5
    },
    "season_to_date": {
      "wins": 17,
      "losses": 27,
      "hit_rate": 0.386
    }
  },
  "generated_at": "2026-03-11"
}